[
  {
    "feNo": "FE-01",
    "area": "Stock yard",
    "location": "metering Room",
    "feType": "CO2",
    "capacity": "5KG",
    "pressureCondition": "",
    "safetySeal": "",
    "maintainedFreeOfObstruction:": "",
    "clearTags": "",
    "physicalDamage": "",
    "refillDate": "",
    "nextRefillDate": "",
    "inspectionDate": "",
    "remarks": ""
  },
  {
    "feNo": "FE-02",
    "area": "Stock yard",
    "location": "Sliting Machine-Column-03",
    "feType": "DCP",
    "capacity": "5KG",
    "pressureCondition": "",
    "safetySeal": "",
    "maintainedFreeOfObstruction:": "",
    "clearTags": "",
    "physicalDamage": "",
    "refillDate": "",
    "nextRefillDate": "",
    "inspectionDate": "",
    "remarks": ""
  },
  {
    "feNo": "FE-03",
    "area": "Stock yard",
    "location": "Sliting Machine-Column-08",
    "feType": "CO2",
    "capacity": "5KG",
    "pressureCondition": "",
    "safetySeal": "",
    "maintainedFreeOfObstruction:": "",
    "clearTags": "",
    "physicalDamage": "",
    "refillDate": "",
    "nextRefillDate": "",
    "inspectionDate": "",
    "remarks": ""
  },
  {
    "feNo": "FE-04",
    "area": "Stock yard",
    "location": "Sliting Machine-Column-13",
    "feType": "DCP",
    "capacity": "5KG",
    "pressureCondition": "",
    "safetySeal": "",
    "maintainedFreeOfObstruction:": "",
    "clearTags": "",
    "physicalDamage": "",
    "refillDate": "",
    "nextRefillDate": "",
    "inspectionDate": "",
    "remarks": ""
  },
  {
    "feNo": "FE-44",
    "area": "Stock yard",
    "location": "Infront of HT Metering Room",
    "feType": "CO2",
    "capacity": "25KG",
    "pressureCondition": "",
    "safetySeal": "",
    "maintainedFreeOfObstruction:": "",
    "clearTags": "",
    "physicalDamage": "",
    "refillDate": "",
    "nextRefillDate": "",
    "inspectionDate": "",
    "remarks": ""
  },
  {
    "feNo": "FE-05",
    "area": "JMI Cylinders Manufacturing Hall",
    "location": "Main Gate Door- 1",
    "feType": "DCP",
    "capacity": "5KG",
    "pressureCondition": "",
    "safetySeal": "",
    "maintainedFreeOfObstruction:": "",
    "clearTags": "",
    "physicalDamage": "",
    "refillDate": "",
    "nextRefillDate": "",
    "inspectionDate": "",
    "remarks": ""
  },
  {
    "feNo": "FE-06",
    "area": "JMI Cylinders Manufacturing Hall",
    "location": "Column-5(Backside of Painting Oven)",
    "feType": "CO2",
    "capacity": "5KG",
    "pressureCondition": "",
    "safetySeal": "",
    "maintainedFreeOfObstruction:": "",
    "clearTags": "",
    "physicalDamage": "",
    "refillDate": "",
    "nextRefillDate": "",
    "inspectionDate": "",
    "remarks": ""
  },
  {
    "feNo": "FE-07",
    "area": "JMI Cylinders Manufacturing Hall",
    "location": "Column-9(Door-2)",
    "feType": "CO2",
    "capacity": "5KG",
    "pressureCondition": "",
    "safetySeal": "",
    "maintainedFreeOfObstruction:": "",
    "clearTags": "",
    "physicalDamage": "",
    "refillDate": "",
    "nextRefillDate": "",
    "inspectionDate": "",
    "remarks": ""
  },
  {
    "feNo": "FE-08",
    "area": "JMI Cylinders Manufacturing Hall",
    "location": "Column-12(Zinc Spary Machine)",
    "feType": "DCP",
    "capacity": "6KG",
    "pressureCondition": "",
    "safetySeal": "",
    "maintainedFreeOfObstruction:": "",
    "clearTags": "",
    "physicalDamage": "",
    "refillDate": "",
    "nextRefillDate": "",
    "inspectionDate": "",
    "remarks": ""
  },
  {
    "feNo": "FE-84",
    "area": "JMI Cylinders Manufacturing Hall",
    "location": "Column-12(Zinc Spary Machine)",
    "feType": "CO2",
    "capacity": "5KG",
    "pressureCondition": "",
    "safetySeal": "",
    "maintainedFreeOfObstruction:": "",
    "clearTags": "",
    "physicalDamage": "",
    "refillDate": "",
    "nextRefillDate": "",
    "inspectionDate": "",
    "remarks": ""
  },
  {
    "feNo": "FE-09",
    "area": "JMI Cylinders Manufacturing Hall",
    "location": "Column-14(Shot Blasting Door-4)",
    "feType": "DCP",
    "capacity": "5KG",
    "pressureCondition": "",
    "safetySeal": "",
    "maintainedFreeOfObstruction:": "",
    "clearTags": "",
    "physicalDamage": "",
    "refillDate": "",
    "nextRefillDate": "",
    "inspectionDate": "",
    "remarks": ""
  },
  {
    "feNo": "FE-10",
    "area": "JMI Cylinders Manufacturing Hall",
    "location": "Column-14(Shot Blasting Door-4)",
    "feType": "CO2",
    "capacity": "5KG",
    "pressureCondition": "",
    "safetySeal": "",
    "maintainedFreeOfObstruction:": "",
    "clearTags": "",
    "physicalDamage": "",
    "refillDate": "",
    "nextRefillDate": "",
    "inspectionDate": "",
    "remarks": ""
  },
  {
    "feNo": "FE-11",
    "area": "JMI Cylinders Manufacturing Hall",
    "location": "Column-18(Heat Treatment)",
    "feType": "CO2",
    "capacity": "5KG",
    "pressureCondition": "",
    "safetySeal": "",
    "maintainedFreeOfObstruction:": "",
    "clearTags": "",
    "physicalDamage": "",
    "refillDate": "",
    "nextRefillDate": "",
    "inspectionDate": "",
    "remarks": ""
  },
  {
    "feNo": "FE-12",
    "area": "JMI Cylinders Manufacturing Hall",
    "location": "Column-22(Body Welding Machine-10)",
    "feType": "CO2",
    "capacity": "5KG",
    "pressureCondition": "",
    "safetySeal": "",
    "maintainedFreeOfObstruction:": "",
    "clearTags": "",
    "physicalDamage": "",
    "refillDate": "",
    "nextRefillDate": "",
    "inspectionDate": "",
    "remarks": ""
  },
  {
    "feNo": "FE-13",
    "area": "JMI Cylinders Manufacturing Hall",
    "location": "Column-24(Body Welding Machine-02)",
    "feType": "DCP",
    "capacity": "5KG",
    "pressureCondition": "",
    "safetySeal": "",
    "maintainedFreeOfObstruction:": "",
    "clearTags": "",
    "physicalDamage": "",
    "refillDate": "",
    "nextRefillDate": "",
    "inspectionDate": "",
    "remarks": ""
  },
  {
    "feNo": "FE-14",
    "area": "JMI Cylinders Manufacturing Hall",
    "location": "Column-25(Upside Platfrom)",
    "feType": "CO2",
    "capacity": "5KG",
    "pressureCondition": "",
    "safetySeal": "",
    "maintainedFreeOfObstruction:": "",
    "clearTags": "",
    "physicalDamage": "",
    "refillDate": "",
    "nextRefillDate": "",
    "inspectionDate": "",
    "remarks": ""
  },
  {
    "feNo": "FE-15",
    "area": "JMI Cylinders Manufacturing Hall",
    "location": "Column-25(Upside Platfrom)",
    "feType": "CO2",
    "capacity": "5KG",
    "pressureCondition": "",
    "safetySeal": "",
    "maintainedFreeOfObstruction:": "",
    "clearTags": "",
    "physicalDamage": "",
    "refillDate": "",
    "nextRefillDate": "",
    "inspectionDate": "",
    "remarks": ""
  },
  {
    "feNo": "FE-16",
    "area": "JMI Cylinders Manufacturing Hall",
    "location": "Column-27(Degreasing Machine)",
    "feType": "DCP",
    "capacity": "6KG",
    "pressureCondition": "",
    "safetySeal": "",
    "maintainedFreeOfObstruction:": "",
    "clearTags": "",
    "physicalDamage": "",
    "refillDate": "",
    "nextRefillDate": "",
    "inspectionDate": "",
    "remarks": ""
  },
  {
    "feNo": "FE-17",
    "area": "JMI Cylinders Manufacturing Hall",
    "location": "Column-32(Deep Drawing Machine-03)",
    "feType": "Foam",
    "capacity": "10L",
    "pressureCondition": "",
    "safetySeal": "",
    "maintainedFreeOfObstruction:": "",
    "clearTags": "",
    "physicalDamage": "",
    "refillDate": "",
    "nextRefillDate": "",
    "inspectionDate": "",
    "remarks": ""
  },
  {
    "feNo": "FE-18",
    "area": "JMI Cylinders Manufacturing Hall",
    "location": "Column-52(Deep Drawing Machine-01)",
    "feType": "Foam",
    "capacity": "10L",
    "pressureCondition": "",
    "safetySeal": "",
    "maintainedFreeOfObstruction:": "",
    "clearTags": "",
    "physicalDamage": "",
    "refillDate": "",
    "nextRefillDate": "",
    "inspectionDate": "",
    "remarks": ""
  },
  {
    "feNo": "FE-19",
    "area": "JMI Cylinders Manufacturing Hall",
    "location": "Column-49(Foot Ring Final Press)",
    "feType": "DCP",
    "capacity": "5KG",
    "pressureCondition": "",
    "safetySeal": "",
    "maintainedFreeOfObstruction:": "",
    "clearTags": "",
    "physicalDamage": "",
    "refillDate": "",
    "nextRefillDate": "",
    "inspectionDate": "",
    "remarks": ""
  },
  {
    "feNo": "FE-20",
    "area": "JMI Cylinders Manufacturing Hall",
    "location": "Column-47(Power Setting Machine)",
    "feType": "CO2",
    "capacity": "5KG",
    "pressureCondition": "",
    "safetySeal": "",
    "maintainedFreeOfObstruction:": "",
    "clearTags": "",
    "physicalDamage": "",
    "refillDate": "",
    "nextRefillDate": "",
    "inspectionDate": "",
    "remarks": ""
  },
  {
    "feNo": "FE-21",
    "area": "JMI Cylinders Manufacturing Hall",
    "location": "Column-42(Hydro test Machine)",
    "feType": "DCP",
    "capacity": "5KG",
    "pressureCondition": "",
    "safetySeal": "",
    "maintainedFreeOfObstruction:": "",
    "clearTags": "",
    "physicalDamage": "",
    "refillDate": "",
    "nextRefillDate": "",
    "inspectionDate": "",
    "remarks": ""
  },
  {
    "feNo": "FE-22",
    "area": "JMI Cylinders Manufacturing Hall",
    "location": "Column-35(Blanking  Machine)",
    "feType": "Foam",
    "capacity": "10L",
    "pressureCondition": "",
    "safetySeal": "",
    "maintainedFreeOfObstruction:": "",
    "clearTags": "",
    "physicalDamage": "",
    "refillDate": "",
    "nextRefillDate": "",
    "inspectionDate": "",
    "remarks": ""
  },
  {
    "feNo": "FE-23",
    "area": "JMI Cylinders Manufacturing Hall",
    "location": "Column-37(Blanking  Machine)",
    "feType": "Foam",
    "capacity": "10L",
    "pressureCondition": "",
    "safetySeal": "",
    "maintainedFreeOfObstruction:": "",
    "clearTags": "",
    "physicalDamage": "",
    "refillDate": "",
    "nextRefillDate": "",
    "inspectionDate": "",
    "remarks": ""
  },
  {
    "feNo": "FE-24",
    "area": "JMI Cylinders Manufacturing Hall",
    "location": "Column-40(CMP Main Gate)",
    "feType": "DCP",
    "capacity": "5KG",
    "pressureCondition": "",
    "safetySeal": "",
    "maintainedFreeOfObstruction:": "",
    "clearTags": "",
    "physicalDamage": "",
    "refillDate": "",
    "nextRefillDate": "",
    "inspectionDate": "",
    "remarks": ""
  },
  {
    "feNo": "FE-25",
    "area": "JMI Sankur Auto Manufacturing Hall",
    "location": "Auto Tank Main Enterence",
    "feType": "Foam",
    "capacity": "10L",
    "pressureCondition": "",
    "safetySeal": "",
    "maintainedFreeOfObstruction:": "",
    "clearTags": "",
    "physicalDamage": "",
    "refillDate": "",
    "nextRefillDate": "",
    "inspectionDate": "",
    "remarks": ""
  },
  {
    "feNo": "FE-26",
    "area": "JMI Sankur Auto Manufacturing Hall",
    "location": "Assembly Point",
    "feType": "CO2",
    "capacity": "5KG",
    "pressureCondition": "",
    "safetySeal": "",
    "maintainedFreeOfObstruction:": "",
    "clearTags": "",
    "physicalDamage": "",
    "refillDate": "",
    "nextRefillDate": "",
    "inspectionDate": "",
    "remarks": ""
  },
  {
    "feNo": "FE-27",
    "area": "JMI Sankur Auto Manufacturing Hall",
    "location": "Trodial Body",
    "feType": "CO2",
    "capacity": "5KG",
    "pressureCondition": "",
    "safetySeal": "",
    "maintainedFreeOfObstruction:": "",
    "clearTags": "",
    "physicalDamage": "",
    "refillDate": "",
    "nextRefillDate": "",
    "inspectionDate": "",
    "remarks": ""
  },
  {
    "feNo": "FE-28",
    "area": "JMI Sankur Auto Manufacturing Hall",
    "location": "Leak Test Machine(Adjacent Door-2)",
    "feType": "CO2",
    "capacity": "5KG",
    "pressureCondition": "",
    "safetySeal": "",
    "maintainedFreeOfObstruction:": "",
    "clearTags": "",
    "physicalDamage": "",
    "refillDate": "",
    "nextRefillDate": "",
    "inspectionDate": "",
    "remarks": ""
  },
  {
    "feNo": "FE-29",
    "area": "JMI Sankur Auto Manufacturing Hall",
    "location": "Pakaging Side",
    "feType": "Foam",
    "capacity": "10L",
    "pressureCondition": "",
    "safetySeal": "",
    "maintainedFreeOfObstruction:": "",
    "clearTags": "",
    "physicalDamage": "",
    "refillDate": "",
    "nextRefillDate": "",
    "inspectionDate": "",
    "remarks": ""
  },
  {
    "feNo": "FE-30",
    "area": "JMI Sankur Auto Manufacturing Hall",
    "location": "Painting line-Door-3",
    "feType": "Foam",
    "capacity": "10L",
    "pressureCondition": "",
    "safetySeal": "",
    "maintainedFreeOfObstruction:": "",
    "clearTags": "",
    "physicalDamage": "",
    "refillDate": "",
    "nextRefillDate": "",
    "inspectionDate": "",
    "remarks": ""
  },
  {
    "feNo": "FE-31",
    "area": "JMI Sankur Auto Manufacturing Hall",
    "location": "Painting lilne Door-4",
    "feType": "CO2",
    "capacity": "5KG",
    "pressureCondition": "",
    "safetySeal": "",
    "maintainedFreeOfObstruction:": "",
    "clearTags": "",
    "physicalDamage": "",
    "refillDate": "",
    "nextRefillDate": "",
    "inspectionDate": "",
    "remarks": ""
  },
  {
    "feNo": "FE-32",
    "area": "JMI Sankur Auto Manufacturing Hall",
    "location": "Shot Blasting Door-5",
    "feType": "DCP",
    "capacity": "5KG",
    "pressureCondition": "",
    "safetySeal": "",
    "maintainedFreeOfObstruction:": "",
    "clearTags": "",
    "physicalDamage": "",
    "refillDate": "",
    "nextRefillDate": "",
    "inspectionDate": "",
    "remarks": ""
  },
  {
    "feNo": "FE-33",
    "area": "JMI Sankur Auto Manufacturing Hall",
    "location": "Hydro Test(35kg & 45kg)-Door-06",
    "feType": "DCP",
    "capacity": "5KG",
    "pressureCondition": "",
    "safetySeal": "",
    "maintainedFreeOfObstruction:": "",
    "clearTags": "",
    "physicalDamage": "",
    "refillDate": "",
    "nextRefillDate": "",
    "inspectionDate": "",
    "remarks": ""
  },
  {
    "feNo": "FE-67",
    "area": "JMI Sankur Auto Manufacturing Hall",
    "location": "Body Welding Machine Door-07",
    "feType": "CO2",
    "capacity": "5KG",
    "pressureCondition": "",
    "safetySeal": "",
    "maintainedFreeOfObstruction:": "",
    "clearTags": "",
    "physicalDamage": "",
    "refillDate": "",
    "nextRefillDate": "",
    "inspectionDate": "",
    "remarks": ""
  },
  {
    "feNo": "FE-34",
    "area": "JMI Sankur Auto Manufacturing Hall",
    "location": "Body Welding Machine Door-07",
    "feType": "CO2",
    "capacity": "25KG",
    "pressureCondition": "",
    "safetySeal": "",
    "maintainedFreeOfObstruction:": "",
    "clearTags": "",
    "physicalDamage": "",
    "refillDate": "",
    "nextRefillDate": "",
    "inspectionDate": "",
    "remarks": ""
  },
  {
    "feNo": "FE-35",
    "area": "JMI Sankur Auto Manufacturing Hall",
    "location": "Reparing Area(Left side Column-2) tools and Dye",
    "feType": "DCP",
    "capacity": "6KG",
    "pressureCondition": "",
    "safetySeal": "",
    "maintainedFreeOfObstruction:": "",
    "clearTags": "",
    "physicalDamage": "",
    "refillDate": "",
    "nextRefillDate": "",
    "inspectionDate": "",
    "remarks": ""
  },
  {
    "feNo": "FE-66",
    "area": "JMI Sankur Auto Manufacturing Hall",
    "location": "JSATL body welding-Door-08",
    "feType": "CO2",
    "capacity": "5KG",
    "pressureCondition": "",
    "safetySeal": "",
    "maintainedFreeOfObstruction:": "",
    "clearTags": "",
    "physicalDamage": "",
    "refillDate": "",
    "nextRefillDate": "",
    "inspectionDate": "",
    "remarks": ""
  },
  {
    "feNo": "FE-36",
    "area": "Validation Hall",
    "location": "Main Enterence",
    "feType": "Foam",
    "capacity": "10L",
    "pressureCondition": "",
    "safetySeal": "",
    "maintainedFreeOfObstruction:": "",
    "clearTags": "",
    "physicalDamage": "",
    "refillDate": "",
    "nextRefillDate": "",
    "inspectionDate": "",
    "remarks": ""
  },
  {
    "feNo": "FE-37",
    "area": "Validation Hall",
    "location": "Door-1",
    "feType": "DCP",
    "capacity": "5KG",
    "pressureCondition": "",
    "safetySeal": "",
    "maintainedFreeOfObstruction:": "",
    "clearTags": "",
    "physicalDamage": "",
    "refillDate": "",
    "nextRefillDate": "",
    "inspectionDate": "",
    "remarks": ""
  },
  {
    "feNo": "FE-38",
    "area": "Validation Hall",
    "location": "Door-2",
    "feType": "CO2",
    "capacity": "5KG",
    "pressureCondition": "",
    "safetySeal": "",
    "maintainedFreeOfObstruction:": "",
    "clearTags": "",
    "physicalDamage": "",
    "refillDate": "",
    "nextRefillDate": "",
    "inspectionDate": "",
    "remarks": ""
  },
  {
    "feNo": "FE-39",
    "area": "Validation Hall",
    "location": "Door-3",
    "feType": "Foam",
    "capacity": "10L",
    "pressureCondition": "",
    "safetySeal": "",
    "maintainedFreeOfObstruction:": "",
    "clearTags": "",
    "physicalDamage": "",
    "refillDate": "",
    "nextRefillDate": "",
    "inspectionDate": "",
    "remarks": ""
  },
  {
    "feNo": "FE-40",
    "area": "Utility Building",
    "location": "Substation Outter Wall",
    "feType": "CO2",
    "capacity": "5KG",
    "pressureCondition": "",
    "safetySeal": "",
    "maintainedFreeOfObstruction:": "",
    "clearTags": "",
    "physicalDamage": "",
    "refillDate": "",
    "nextRefillDate": "",
    "inspectionDate": "",
    "remarks": ""
  },
  {
    "feNo": "FE-41",
    "area": "Utility Building",
    "location": "Main Enterence",
    "feType": "CO2",
    "capacity": "25KG",
    "pressureCondition": "",
    "safetySeal": "",
    "maintainedFreeOfObstruction:": "",
    "clearTags": "",
    "physicalDamage": "",
    "refillDate": "",
    "nextRefillDate": "",
    "inspectionDate": "",
    "remarks": ""
  },
  {
    "feNo": "FE-42",
    "area": "Utility Building",
    "location": "Main Enterence",
    "feType": "CO2",
    "capacity": "5KG",
    "pressureCondition": "",
    "safetySeal": "",
    "maintainedFreeOfObstruction:": "",
    "clearTags": "",
    "physicalDamage": "",
    "refillDate": "",
    "nextRefillDate": "",
    "inspectionDate": "",
    "remarks": ""
  },
  {
    "feNo": "FE-43",
    "area": "Generator Room",
    "location": "Enterence Door-1",
    "feType": "Foam",
    "capacity": "10L",
    "pressureCondition": "",
    "safetySeal": "",
    "maintainedFreeOfObstruction:": "",
    "clearTags": "",
    "physicalDamage": "",
    "refillDate": "",
    "nextRefillDate": "",
    "inspectionDate": "",
    "remarks": ""
  },
  {
    "feNo": "FE-45",
    "area": "Compressor Room",
    "location": "Main Enterence",
    "feType": "CO2",
    "capacity": "5KG",
    "pressureCondition": "",
    "safetySeal": "",
    "maintainedFreeOfObstruction:": "",
    "clearTags": "",
    "physicalDamage": "",
    "refillDate": "",
    "nextRefillDate": "",
    "inspectionDate": "",
    "remarks": ""
  },
  {
    "feNo": "FE-46",
    "area": "",
    "location": "Middle Column",
    "feType": "CO2",
    "capacity": "5KG",
    "pressureCondition": "",
    "safetySeal": "",
    "maintainedFreeOfObstruction:": "",
    "clearTags": "",
    "physicalDamage": "",
    "refillDate": "",
    "nextRefillDate": "",
    "inspectionDate": "",
    "remarks": ""
  },
  {
    "feNo": "FE-47",
    "area": "Store",
    "location": "Store office Enterence Right wall",
    "feType": "DCP",
    "capacity": "5KG",
    "pressureCondition": "",
    "safetySeal": "",
    "maintainedFreeOfObstruction:": "",
    "clearTags": "",
    "physicalDamage": "",
    "refillDate": "",
    "nextRefillDate": "",
    "inspectionDate": "",
    "remarks": ""
  },
  {
    "feNo": "FE-48",
    "area": "Store",
    "location": "Store office Enterence Right wall",
    "feType": "CO2",
    "capacity": "5KG",
    "pressureCondition": "",
    "safetySeal": "",
    "maintainedFreeOfObstruction:": "",
    "clearTags": "",
    "physicalDamage": "",
    "refillDate": "",
    "nextRefillDate": "",
    "inspectionDate": "",
    "remarks": ""
  },
  {
    "feNo": "FE-49",
    "area": "Store",
    "location": "Chemical Storage Room",
    "feType": "Foam",
    "capacity": "10L",
    "pressureCondition": "",
    "safetySeal": "",
    "maintainedFreeOfObstruction:": "",
    "clearTags": "",
    "physicalDamage": "",
    "refillDate": "",
    "nextRefillDate": "",
    "inspectionDate": "",
    "remarks": ""
  },
  {
    "feNo": "FE-50",
    "area": "Store",
    "location": "1st Floor",
    "feType": "DCP",
    "capacity": "5KG",
    "pressureCondition": "",
    "safetySeal": "",
    "maintainedFreeOfObstruction:": "",
    "clearTags": "",
    "physicalDamage": "",
    "refillDate": "",
    "nextRefillDate": "",
    "inspectionDate": "",
    "remarks": ""
  },
  {
    "feNo": "FE-51",
    "area": "QC LAB",
    "location": "Main Hall (UTM and Brusting Machine Area)",
    "feType": "DCP",
    "capacity": "5KG",
    "pressureCondition": "",
    "safetySeal": "",
    "maintainedFreeOfObstruction:": "",
    "clearTags": "",
    "physicalDamage": "",
    "refillDate": "",
    "nextRefillDate": "",
    "inspectionDate": "",
    "remarks": ""
  },
  {
    "feNo": "FE-52",
    "area": "QC LAB",
    "location": "Main Hall (UTM and Brusting Machine Area)",
    "feType": "DCP",
    "capacity": "5KG",
    "pressureCondition": "",
    "safetySeal": "",
    "maintainedFreeOfObstruction:": "",
    "clearTags": "",
    "physicalDamage": "",
    "refillDate": "",
    "nextRefillDate": "",
    "inspectionDate": "",
    "remarks": ""
  },
  {
    "feNo": "FE-53",
    "area": "Admin Building",
    "location": "Ground Floor Lift lobby",
    "feType": "DCP",
    "capacity": "5KG",
    "pressureCondition": "",
    "safetySeal": "",
    "maintainedFreeOfObstruction:": "",
    "clearTags": "",
    "physicalDamage": "",
    "refillDate": "",
    "nextRefillDate": "",
    "inspectionDate": "",
    "remarks": ""
  },
  {
    "feNo": "FE-54",
    "area": "Admin Building",
    "location": "Kitchen Hall",
    "feType": "Wet Chemical",
    "capacity": "5KG",
    "pressureCondition": "",
    "safetySeal": "",
    "maintainedFreeOfObstruction:": "",
    "clearTags": "",
    "physicalDamage": "",
    "refillDate": "",
    "nextRefillDate": "",
    "inspectionDate": "",
    "remarks": ""
  },
  {
    "feNo": "FE-55",
    "area": "Admin Building",
    "location": "Kitchen Hall (Door Side Outter Wall)",
    "feType": "Wet Chemical",
    "capacity": "5KG",
    "pressureCondition": "",
    "safetySeal": "",
    "maintainedFreeOfObstruction:": "",
    "clearTags": "",
    "physicalDamage": "",
    "refillDate": "",
    "nextRefillDate": "",
    "inspectionDate": "",
    "remarks": ""
  },
  {
    "feNo": "FE-57",
    "area": "Admin Building",
    "location": "1st Floor",
    "feType": "DCP",
    "capacity": "5KG",
    "pressureCondition": "",
    "safetySeal": "",
    "maintainedFreeOfObstruction:": "",
    "clearTags": "",
    "physicalDamage": "",
    "refillDate": "",
    "nextRefillDate": "",
    "inspectionDate": "",
    "remarks": ""
  },
  {
    "feNo": "FE-58",
    "area": "Admin Building",
    "location": "1nd Floor",
    "feType": "CO2",
    "capacity": "5KG",
    "pressureCondition": "",
    "safetySeal": "",
    "maintainedFreeOfObstruction:": "",
    "clearTags": "",
    "physicalDamage": "",
    "refillDate": "",
    "nextRefillDate": "",
    "inspectionDate": "",
    "remarks": ""
  },
  {
    "feNo": "FE-59",
    "area": "Admin Building",
    "location": "2nd Floor",
    "feType": "DCP",
    "capacity": "5KG",
    "pressureCondition": "",
    "safetySeal": "",
    "maintainedFreeOfObstruction:": "",
    "clearTags": "",
    "physicalDamage": "",
    "refillDate": "",
    "nextRefillDate": "",
    "inspectionDate": "",
    "remarks": ""
  },
  {
    "feNo": "FE-60",
    "area": "Admin Building",
    "location": "2rd Floor",
    "feType": "CO2",
    "capacity": "5KG",
    "pressureCondition": "",
    "safetySeal": "",
    "maintainedFreeOfObstruction:": "",
    "clearTags": "",
    "physicalDamage": "",
    "refillDate": "",
    "nextRefillDate": "",
    "inspectionDate": "",
    "remarks": ""
  },
  {
    "feNo": "FE-61",
    "area": "Admin Building",
    "location": "3rd Floor",
    "feType": "DCP",
    "capacity": "5KG",
    "pressureCondition": "",
    "safetySeal": "",
    "maintainedFreeOfObstruction:": "",
    "clearTags": "",
    "physicalDamage": "",
    "refillDate": "",
    "nextRefillDate": "",
    "inspectionDate": "",
    "remarks": ""
  },
  {
    "feNo": "FE-62",
    "area": "Admin Building",
    "location": "3th Floor",
    "feType": "CO2",
    "capacity": "5KG",
    "pressureCondition": "",
    "safetySeal": "",
    "maintainedFreeOfObstruction:": "",
    "clearTags": "",
    "physicalDamage": "",
    "refillDate": "",
    "nextRefillDate": "",
    "inspectionDate": "",
    "remarks": ""
  },
  {
    "feNo": "FE-63",
    "area": "Admin Building",
    "location": "4th Floor",
    "feType": "DCP",
    "capacity": "5KG",
    "pressureCondition": "",
    "safetySeal": "",
    "maintainedFreeOfObstruction:": "",
    "clearTags": "",
    "physicalDamage": "",
    "refillDate": "",
    "nextRefillDate": "",
    "inspectionDate": "",
    "remarks": ""
  },
  {
    "feNo": "FE-64",
    "area": "Admin Building",
    "location": "4th Floor",
    "feType": "CO2",
    "capacity": "5KG",
    "pressureCondition": "",
    "safetySeal": "",
    "maintainedFreeOfObstruction:": "",
    "clearTags": "",
    "physicalDamage": "",
    "refillDate": "",
    "nextRefillDate": "",
    "inspectionDate": "",
    "remarks": ""
  },
  {
    "feNo": "FE-65",
    "area": "Common Area",
    "location": "Security Gate",
    "feType": "DCP",
    "capacity": "5KG",
    "pressureCondition": "",
    "safetySeal": "",
    "maintainedFreeOfObstruction:": "",
    "clearTags": "",
    "physicalDamage": "",
    "refillDate": "",
    "nextRefillDate": "",
    "inspectionDate": "",
    "remarks": ""
  },
  {
    "feNo": "FE-68",
    "area": "Common Area",
    "location": "Pump House",
    "feType": "DCP",
    "capacity": "5KG",
    "pressureCondition": "",
    "safetySeal": "",
    "maintainedFreeOfObstruction:": "",
    "clearTags": "",
    "physicalDamage": "",
    "refillDate": "",
    "nextRefillDate": "",
    "inspectionDate": "",
    "remarks": ""
  },
  {
    "feNo": "FE-69",
    "area": "Common Area",
    "location": "Pump House",
    "feType": "Foam",
    "capacity": "10L",
    "pressureCondition": "",
    "safetySeal": "",
    "maintainedFreeOfObstruction:": "",
    "clearTags": "",
    "physicalDamage": "",
    "refillDate": "",
    "nextRefillDate": "",
    "inspectionDate": "",
    "remarks": ""
  },
  {
    "feNo": "FE-70",
    "area": "Common Area",
    "location": "Work Shop",
    "feType": "Foam",
    "capacity": "10L",
    "pressureCondition": "",
    "safetySeal": "",
    "maintainedFreeOfObstruction:": "",
    "clearTags": "",
    "physicalDamage": "",
    "refillDate": "",
    "nextRefillDate": "",
    "inspectionDate": "",
    "remarks": ""
  },
  {
    "feNo": "FE-71",
    "area": "Common Area",
    "location": "Work Shop",
    "feType": "DCP",
    "capacity": "5KG",
    "pressureCondition": "",
    "safetySeal": "",
    "maintainedFreeOfObstruction:": "",
    "clearTags": "",
    "physicalDamage": "",
    "refillDate": "",
    "nextRefillDate": "",
    "inspectionDate": "",
    "remarks": ""
  },
  {
    "feNo": "FE-72",
    "area": "Common Area",
    "location": "Work Shop Outside Repair Shop",
    "feType": "DCP",
    "capacity": "5KG",
    "pressureCondition": "",
    "safetySeal": "",
    "maintainedFreeOfObstruction:": "",
    "clearTags": "",
    "physicalDamage": "",
    "refillDate": "",
    "nextRefillDate": "",
    "inspectionDate": "",
    "remarks": ""
  },
  {
    "feNo": "FE-56",
    "area": "Dormitory",
    "location": "block -A",
    "feType": "DCP",
    "capacity": "5KG",
    "pressureCondition": "",
    "safetySeal": "",
    "maintainedFreeOfObstruction:": "",
    "clearTags": "",
    "physicalDamage": "",
    "refillDate": "",
    "nextRefillDate": "",
    "inspectionDate": "",
    "remarks": ""
  },
  {
    "feNo": "FE-73",
    "area": "Dormitory",
    "location": "block -B",
    "feType": "DCP",
    "capacity": "5KG",
    "pressureCondition": "",
    "safetySeal": "",
    "maintainedFreeOfObstruction:": "",
    "clearTags": "",
    "physicalDamage": "",
    "refillDate": "",
    "nextRefillDate": "",
    "inspectionDate": "",
    "remarks": ""
  },
  {
    "feNo": "FE-74",
    "area": "Dormitory",
    "location": "block -C",
    "feType": "DCP",
    "capacity": "5KG",
    "pressureCondition": "",
    "safetySeal": "",
    "maintainedFreeOfObstruction:": "",
    "clearTags": "",
    "physicalDamage": "",
    "refillDate": "",
    "nextRefillDate": "",
    "inspectionDate": "",
    "remarks": ""
  },
  {
    "feNo": "FE-75",
    "area": "Dormitory",
    "location": "block -D",
    "feType": "DCP",
    "capacity": "5KG",
    "pressureCondition": "",
    "safetySeal": "",
    "maintainedFreeOfObstruction:": "",
    "clearTags": "",
    "physicalDamage": "",
    "refillDate": "",
    "nextRefillDate": "",
    "inspectionDate": "",
    "remarks": ""
  },
  {
    "feNo": "FE-76",
    "area": "Dormitory",
    "location": "Kitchen Hall",
    "feType": "DCP",
    "capacity": "5KG",
    "pressureCondition": "",
    "safetySeal": "",
    "maintainedFreeOfObstruction:": "",
    "clearTags": "",
    "physicalDamage": "",
    "refillDate": "",
    "nextRefillDate": "",
    "inspectionDate": "",
    "remarks": ""
  },
  {
    "feNo": "FE-77",
    "area": "Dormitory",
    "location": "Kitchen Hall",
    "feType": "Wet Chemical",
    "capacity": "5KG",
    "pressureCondition": "",
    "safetySeal": "",
    "maintainedFreeOfObstruction:": "",
    "clearTags": "",
    "physicalDamage": "",
    "refillDate": "",
    "nextRefillDate": "",
    "inspectionDate": "",
    "remarks": ""
  },
  {
    "feNo": "FE-78",
    "area": "Microw Bus",
    "location": "No- 56-6349",
    "feType": "DCP",
    "capacity": "2kg",
    "pressureCondition": "",
    "safetySeal": "",
    "maintainedFreeOfObstruction:": "",
    "clearTags": "",
    "physicalDamage": "",
    "refillDate": "",
    "nextRefillDate": "",
    "inspectionDate": "",
    "remarks": ""
  },
  {
    "feNo": "FE-79",
    "area": "Microw Bus",
    "location": "No- 56-4674",
    "feType": "DCP",
    "capacity": "2kg",
    "pressureCondition": "",
    "safetySeal": "",
    "maintainedFreeOfObstruction:": "",
    "clearTags": "",
    "physicalDamage": "",
    "refillDate": "",
    "nextRefillDate": "",
    "inspectionDate": "",
    "remarks": ""
  },
  {
    "feNo": "FE-80",
    "area": "Microw Bus",
    "location": "No- 56-4398",
    "feType": "DCP",
    "capacity": "2kg",
    "pressureCondition": "",
    "safetySeal": "",
    "maintainedFreeOfObstruction:": "",
    "clearTags": "",
    "physicalDamage": "",
    "refillDate": "",
    "nextRefillDate": "",
    "inspectionDate": "",
    "remarks": ""
  },
  {
    "feNo": "FE-81",
    "area": "Cover van",
    "location": "No- 115917",
    "feType": "DCP",
    "capacity": "5KG",
    "pressureCondition": "",
    "safetySeal": "",
    "maintainedFreeOfObstruction:": "",
    "clearTags": "",
    "physicalDamage": "",
    "refillDate": "",
    "nextRefillDate": "",
    "inspectionDate": "",
    "remarks": ""
  },
  {
    "feNo": "FE-82",
    "area": "Truck",
    "location": "No- 11-5464",
    "feType": "DCP",
    "capacity": "5KG",
    "pressureCondition": "",
    "safetySeal": "",
    "maintainedFreeOfObstruction:": "",
    "clearTags": "",
    "physicalDamage": "",
    "refillDate": "",
    "nextRefillDate": "",
    "inspectionDate": "",
    "remarks": ""
  },
  {
    "feNo": "FE-83",
    "area": "Truck",
    "location": "No- 11-5465",
    "feType": "DCP",
    "capacity": "5KG",
    "pressureCondition": "",
    "safetySeal": "",
    "maintainedFreeOfObstruction:": "",
    "clearTags": "",
    "physicalDamage": "",
    "refillDate": "",
    "nextRefillDate": "",
    "inspectionDate": "",
    "remarks": ""
  }
]
